logs_to_ocsf/__init__.py
logs_to_ocsf/_modidx.py
logs_to_ocsf/convert_messages.py
logs_to_ocsf/core.py
logs_to_ocsf-0.0.7.dist-info/LICENSE
logs_to_ocsf-0.0.7.dist-info/METADATA
logs_to_ocsf-0.0.7.dist-info/WHEEL
logs_to_ocsf-0.0.7.dist-info/entry_points.txt
logs_to_ocsf-0.0.7.dist-info/top_level.txt
logs_to_ocsf-0.0.7.dist-info/RECORD
