Metadata-Version: 2.1
Name: logs-to-ocsf
Version: 0.0.7
Summary: Convert Linux logs to OCSF schema
Home-page: https://github.com/javastarchild/logs_to_ocsf
Author: Kelvin
Author-email: javastarchild@gmail.com
License: Apache Software License 2.0
Keywords: nbdev jupyter notebook python
Classifier: Development Status :: 4 - Beta
Classifier: Intended Audience :: Developers
Classifier: Natural Language :: English
Classifier: Programming Language :: Python :: 3.7
Classifier: Programming Language :: Python :: 3.8
Classifier: Programming Language :: Python :: 3.9
Classifier: Programming Language :: Python :: 3.10
Classifier: License :: OSI Approved :: Apache Software License
Requires-Python: >=3.7
License-File: LICENSE
Provides-Extra: dev
